[
    {
        "name": "Lulu",
        "species": "Floatzel-Thievul",
        "extension": "png",
        "artist": {
            "work": "Artist",
            "name": "Fawnidae",
            "url": "https://bsky.app/profile/fawnidae.bsky.social",
            "social": "Bluesky"
        }
    },
    {
        "name": "Chesapeake",
        "species": "Beech Marten",
        "extension": "jpg",
        "artist": {
            "work": "Artist",
            "name": "Loveycloud",
            "url": "https://bsky.app/profile/loveycloud.bsky.social",
            "social": "Bluesky"
        }
    },
    {
        "name": "Kirsche",
        "species": "Amphimorpho",
        "species_url": "https://amphimorpho.carrd.co/",
        "extension": "png",
        "artist": {
            "work": "Base",
            "name": "TuxedoDragon",
            "url": "https://tuxedodragon.art/",
            "social": "Website"
        }
    },
    {
        "name": "Gavin",
        "species": "Jolteon",
        "extension": "jpg"
    },
    {
        "name": "Denver",
        "species": "Train Wolf",
        "extension": "png"
    },
    {
        "name": "Henri",
        "species": "Stoat",
        "extension": "jpg",
        "artist": {
            "work": "Artist",
            "name": "Lennguine",
            "url": "https://bsky.app/profile/lennguine.bsky.social",
            "social": "Bluesky"
        }
    },
    {
        "name": "Millie",
        "species": "Furret",
        "extension": "png",
        "artist": {
            "work": "Artist",
            "name": "Rei",
            "url": "https://bsky.app/profile/kappanuki.bsky.social",
            "social": "Bluesky"
        }
    }
]